[
  {
    "username": "Jennie Dean",
    "place": "Coorg",
    "blogImage": "https://seoimgak.mmtcdn.com/blog/sites/default/files/images/Coorg%20Blog%20Image.jpg",
    "userImage": "https://s3.amazonaws.com/uifaces/faces/twitter/ladylexy/128.jpg",
    "likeCount": 78,
    "commentsCount": 14,
    "caption": "One of the best ways to make a great vacation quickly horrible is to choose the wrong accommodations for your trip.",
    "updateTime": "10min"
  },
  {
    "username": "Garret Gilbert",
    "place": "Goa",
    "blogImage": "https://s32388.pcdn.co/wp-content/uploads/2014/02/how-to-start-travel-blog-tips.jpg",
    "userImage": "https://www.minnesotangos.org/sites/default/files/Allie%20Baker%20Round_1.png",
    "likeCount": 53,
    "commentsCount": 7,
    "caption": "One of the best ways to make a great vacation quickly horrible is to choose the wrong accommodations for your trip.",
    "updateTime": "1hour"
  },
  {
    "username": "Jennie Dean",
    "place": "Greece",
    "blogImage": "https://encrypted-tbn0.gstatic.com/images?q=tbn%3AANd9GcSczNop2KVS4xNaFzsW6AL-Lubgquu3Huawdw&usqp=CAU",
    "userImage": "https://encrypted-tbn0.gstatic.com/images?q=tbn%3AANd9GcSHCO8BXQgCW1bSL43tE5zqRg4_I5Ngnomn2A&usqp=CAU",
    "likeCount": 78,
    "commentsCount": 14,
    "caption": "One of the best ways to make a great vacation quickly horrible is to choose the wrong accommodations for your trip.",
    "updateTime": "40min"
  },
  {
    "username": "Jennie Dean",
    "place": "Coorg",
    "blogImage": "https://s32388.pcdn.co/wp-content/uploads/2014/02/how-to-start-travel-blog-tips.jpg",
    "userImage": "https://encrypted-tbn0.gstatic.com/images?q=tbn%3AANd9GcQONQrFXvU0TQLDbw8QrW7rvcmXWjBS80bX7g&usqp=CAU",
    "likeCount": 78,
    "commentsCount": 14,
    "caption": "One of the best ways to make a great vacation quickly horrible is to choose the wrong accommodations for your trip.",
    "updateTime": "10min"
  },
  {
    "username": "Jennie Dean",
    "place": "Coorg",
    "blogImage": "https://s32388.pcdn.co/wp-content/uploads/2014/02/how-to-start-travel-blog-tips.jpg",
    "userImage": "https://s3.amazonaws.com/uifaces/faces/twitter/ladylexy/128.jpg",
    "likeCount": 78,
    "commentsCount": 14,
    "caption": "One of the best ways to make a great vacation quickly horrible is to choose the wrong accommodations for your trip.",
    "updateTime": "10min"
  }
]
